{
    "abilities": {
        "cobalion": {
            "primary": "Giustizia"
        }
    },
    "curiosities": [
        "Pur non avendo artigli di alcun genere, Cobalion è in grado di apprendere la mossa Ferrartigli aumentando di livello."
    ],
    "cry": "https://play.pokemonshowdown.com/audio/cries/cobalion.mp3",
    "dex_entries": {
        "cobalion": {
            "black": "Pokémon leggendario che ha lottato contro gli umani per difendere i Pokémon. Ha un carattere calmo e controllato.",
            "white": "Ha un corpo e uno spirito d'acciaio. Gli basta lo sguardo per farsi ubbidire anche dai Pokémon più feroci.",
            "black-2": "Ha un corpo e uno spirito d'acciaio. È comparso con i suoi compagni per punire coloro che un tempo ferirono i Pokémon.",
            "white-2": "Ha un corpo e uno spirito d'acciaio. È comparso con i suoi compagni per punire coloro che un tempo ferirono i Pokémon.",
            "x": "Ha un corpo e uno spirito d'acciaio. Gli basta lo sguardo per farsi ubbidire anche dai Pokémon più feroci.",
            "y": "Ha un corpo e uno spirito d'acciaio. È comparso con i suoi compagni per punire coloro che un tempo ferirono i Pokémon.",
            "omega-ruby": "Ha un corpo e uno spirito d'acciaio. Gli basta lo sguardo per farsi ubbidire anche dai Pokémon più feroci.",
            "alpha-sapphire": "Ha un corpo e uno spirito d'acciaio. È comparso con i suoi compagni per punire coloro che un tempo ferirono i Pokémon.",
            "sword": "La leggenda narra che abbia lottato assieme a Terrakion e Virizion contro gli esseri umani per proteggere i Pokémon di Unima.",
            "shield": "È un leader nato. Al suo cospetto anche i Pokémon più feroci assumono un atteggiamento reverenziale."
        }
    },
    "egg_groups": [
        "Sconosciuto"
    ],
    "flat_name": "cobalion",
    "generation": 5,
    "height": {
        "cobalion": "2,1 m"
    },
    "id": 638,
    "name": "Cobalion",
    "name_origin": "Il suo nome potrebbe derivare dall'unione delle parole inglesi cobalt  e champion  o lion . ",
    "origin": "Cobalion è basato sulla figura di Athos, personaggio del racconto \"I tre moschettieri\". Come il suo omonimo è il più anziano e il leader del gruppo. Il suo aspetto ricorda quello del markhor, una grossa capra selvatica afghana, o del kudu maggiore, ma il colore del manto ricorda la pelliccia del lupo grigio, ed è un riferimento esplicito al blu cobalto. ",
    "pokecentral_url": "https://wiki.pokemoncentral.it/Cobalion",
    "shape": "più di 4 arti",
    "specie": "Pokémon Metalcuore",
    "sprites": {
        "cobalion": {
            "default": "https://media.pokemoncentral.it/wiki/d/d0/Homem0638.png",
            "shiny": "https://media.pokemoncentral.it/wiki/c/c6/Homemsh0638.png",
            "corporate": "https://media.pokemoncentral.it/wiki/8/8d/Artwork0638_Corp.png"
        },
        "official_artwork": "https://media.pokemoncentral.it/wiki/5/55/Artwork0638_NB.png"
    },
    "stats": {
        "cobalion": {
            "hp": 91,
            "atk": 90,
            "def": 129,
            "spa": 90,
            "spd": 72,
            "spe": 108
        }
    },
    "stats_sum": {
        "cobalion": 580
    },
    "types": {
        "cobalion": [
            "Lotta",
            "Acciaio"
        ]
    },
    "weight": {
        "cobalion": "250,0 kg"
    }
}