{
    "abilities": {
        "overqwil": {
            "primary": "Velenopunte",
            "secondary": "Nuotovelox",
            "hidden": "Prepotenza"
        }
    },
    "curiosities": [
        "Overqwil presenta una Q sulla coda.",
        "Overqwil, prima della rivelazione ufficiale in Leggende Pokémon: Arceus, era già stato anticipato in Pokémon Diamante Lucente e Perla Splendente, dove è menzionato in uno dei libri nella Biblioteca di Canalipoli. In esso, infatti, si parla di un \"Qwilfish dai lunghi aculei\", laddove gli aculei del Pokémon Pallone sono descritti nei Pokédex di Argento, Rosso Fuoco, SoulSilver, Y e Scudo come piccoli e corti."
    ],
    "cry": "https://play.pokemonshowdown.com/audio/cries/overqwil.mp3",
    "dex_entries": {
        "overqwil": {
            "legends-arceus": "Appellato \"demone dei mari\" per via del feroce temperamento e degli aculei simili a lance, sugge veleno e indi lo converte in nutrimento."
        }
    },
    "egg_groups": [
        "Sconosciuto"
    ],
    "generation": 8,
    "height": {
        "overqwil": "2.5 m"
    },
    "id": 904,
    "name": "Overqwil",
    "name_origin": "Overqwil potrebbe essere una combinazione delle parole over, quill e Qwilfish. Potrebbe essere anche un gioco di parole con overkill. ",
    "origin": "Come Qwilfish si basa su un pesce palla o su un pesce istrice. Il suo aspetto e il fatto che possa apprendere Autodistruzione tramite livello potrebbe rimandare ad una mina navale. ",
    "shape": "sconosciuto",
    "specie": "Pokémon Spinoso",
    "sprites": {
        "overqwil": {
            "default": "https://media.pokemoncentral.it/wiki/b/bd/Homem0904.png",
            "shiny": "https://media.pokemoncentral.it/wiki/e/e9/Homemsh0904.png"
        }
    },
    "stats": {
        "overqwil": {
            "hp": 85,
            "atk": 115,
            "def": 95,
            "spa": 65,
            "spd": 65,
            "spe": 85
        }
    },
    "stats_sum": {
        "overqwil": 510
    },
    "types": {
        "overqwil": [
            "Buio",
            "Veleno"
        ]
    },
    "weight": {
        "overqwil": "60.5 kg"
    }
}